Metadata-Version: 2.4
Name: ugit-cli
Version: 2.0.0
Summary: A minimal Git implementation in Python
Author: night-slayer18
License-Expression: MIT
Project-URL: Homepage, https://github.com/night-slayer18/ugit
Project-URL: Bug Tracker, https://github.com/night-slayer18/ugit/issues
Project-URL: Documentation, https://github.com/night-slayer18/ugit/blob/main/README.md
Project-URL: Source Code, https://github.com/night-slayer18/ugit
Keywords: git,version-control,vcs,educational,minimal
Classifier: Development Status :: 4 - Beta
Classifier: Intended Audience :: Developers
Classifier: Intended Audience :: Education
Classifier: Operating System :: OS Independent
Classifier: Programming Language :: Python :: 3
Classifier: Programming Language :: Python :: 3.9
Classifier: Programming Language :: Python :: 3.10
Classifier: Programming Language :: Python :: 3.11
Classifier: Programming Language :: Python :: 3.12
Classifier: Topic :: Software Development :: Version Control
Classifier: Topic :: Education
Classifier: Topic :: Utilities
Requires-Python: >=3.9
License-File: LICENSE
Provides-Extra: dev
Requires-Dist: pytest>=7.0.0; extra == "dev"
Requires-Dist: pytest-cov>=4.0.0; extra == "dev"
Requires-Dist: black>=22.0.0; extra == "dev"
Requires-Dist: isort>=5.10.0; extra == "dev"
Requires-Dist: flake8>=5.0.0; extra == "dev"
Requires-Dist: mypy>=1.0.0; extra == "dev"
Requires-Dist: pre-commit>=2.20.0; extra == "dev"
Provides-Extra: docs
Requires-Dist: sphinx>=5.0.0; extra == "docs"
Requires-Dist: sphinx-rtd-theme>=1.0.0; extra == "docs"
Provides-Extra: web
Requires-Dist: fastapi>=0.104.1; extra == "web"
Requires-Dist: uvicorn[standard]>=0.24.0; extra == "web"
Requires-Dist: jinja2>=3.1.2; extra == "web"
Requires-Dist: python-multipart>=0.0.6; extra == "web"
Requires-Dist: aiofiles>=23.2.1; extra == "web"
Requires-Dist: httpx>=0.27.0; extra == "web"
Dynamic: license-file
